livyclient/__init__.py
livyclient/batch.py
livyclient/exceptions.py
livyclient/session.py
livyclient/models/__init__.py
livyclient/models/batches.py
livyclient/models/common.py
livyclient/models/sessions.py
livyclient/utils/__init__.py
livyclient/utils/case.py
livyclient/utils/httpclient.py
livyclient-0.0.3.dist-info/LICENSE
livyclient-0.0.3.dist-info/METADATA
livyclient-0.0.3.dist-info/WHEEL
livyclient-0.0.3.dist-info/top_level.txt
livyclient-0.0.3.dist-info/RECORD
