Metadata-Version: 2.1
Name: livyclient
Version: 0.0.3
Summary: A Python client for Apache Livy.
Home-page: https://github.com/deyoulee/livyclient
Author: Deyou Lee
Author-email: deyoulee@126.com
License: GNU GENERAL PUBLIC LICENSE
Requires-Dist: requests (>=2.21.0)
